{
  "$schema": "https://turbo.build/schema.json",
  "ui": "tui",
  "globalEnv": [
    "DATABASE_URL",
    "NEXTAUTH_SECRET",
    "NEXTAUTH_URL",
    "NEXT_PUBLIC_SITE_URL",
    "NEXT_PUBLIC_APP_URL",
    "NEXT_PUBLIC_SERVER_URL",
    "NODE_ENV"
  ],
  "tasks": {
    "build": {
      "dependsOn": ["^build"],
      "inputs": ["$TURBO_DEFAULT$", ".env*"],
      "outputs": ["dist/**", ".next/**", ".output/**"]
    },
    "lint": {
      "dependsOn": ["^lint"]
    },
    "check-types": {
      "dependsOn": ["^check-types"]
    },
    "dev": {
      "cache": false,
      "persistent": true
    },
    "db:push": {
      "cache": false
    },
    "db:studio": {
      "cache": false,
      "persistent": true
    },
    "db:migrate": {
      "cache": false,
      "persistent": true
    },
    "db:generate": {
      "cache": false
    }
  }
}
